syslog_manager/__init__.py
syslog_manager/count_event_per_process.py
syslog_manager/exporter.py
syslog_manager/hourly_report.py
syslog_manager/log_query.py
syslog_manager/main.py
syslog_manager/split_by_day.py
syslog_manager/utility.py
syslog_manager-2.1.1.dist-info/METADATA
syslog_manager-2.1.1.dist-info/WHEEL
syslog_manager-2.1.1.dist-info/entry_points.txt
syslog_manager-2.1.1.dist-info/top_level.txt
syslog_manager-2.1.1.dist-info/RECORD
